{
    "name": "SecurityInfo",
    "version": "3.0.0",
    "description": "Provides security information about your PHP environment and offers suggestions based on PhpSecInfo from the PHP Security Consortium.",
    "keywords": ["security","phpsec"],
    "license": "GPL v3+",
    "homepage": "http://piwik.org",
    "require": {
        "piwik": ">=3.0.0-b1,<4.0.0-b1"
    },

    "support": {
        "issues": "https://github.com/piwik/plugin-SecurityInfo/issues",
        "forum": "https://forum.piwik.org",
        "source": "https://github.com/piwik/plugin-SecurityInfo"
    },
    "authors": [
        {
            "name": "Piwik",
            "email": "hello@piwik.org",
            "homepage": "http://piwik.org"
        }
    ]
}
